noveldown/__init__.py
noveldown/api.py
noveldown/cli.py
noveldown/sources/__init__.py
noveldown/sources/base_source.py
noveldown/sources/source_claw.py
noveldown/sources/source_pale.py
noveldown/sources/source_practical_guide_to_evil.py
noveldown/sources/source_wandering_inn.py
noveldown/utils.py
noveldown-1.3.0.dist-info/LICENSE
noveldown-1.3.0.dist-info/METADATA
noveldown-1.3.0.dist-info/WHEEL
noveldown-1.3.0.dist-info/entry_points.txt
noveldown-1.3.0.dist-info/RECORD
