Metadata-Version: 2.1
Name: noveldown
Version: 1.3.0
Summary: Webnovel downloader and EPUB converter
Home-page: https://github.com/potatoeggy/noveldown
License: LGPL-3.0-only
Keywords: novel,epub,webnovel,download
Author: potatoeggy
Author-email: eggyrules@gmail.com
Requires-Python: >=3.10
Classifier: License :: OSI Approved :: GNU Lesser General Public License v3 (LGPLv3)
Classifier: Programming Language :: Python :: 3
Classifier: Programming Language :: Python :: 3.10
Classifier: Programming Language :: Python :: 3.11
Classifier: Programming Language :: Python :: 3.12
Requires-Dist: EbookLib (>=0.18.0,<0.19.0)
Requires-Dist: beautifulsoup4 (>=4.12.3,<5.0.0)
Requires-Dist: filetype (>=1.2.0,<2.0.0)
Requires-Dist: httpx (>=0.27.2,<0.28.0)
Requires-Dist: lxml (>=5.3.0,<6.0.0)
Requires-Dist: requests (>=2.32.3,<3.0.0)
Requires-Dist: typer (>=0.7.0,<0.8.0)
Project-URL: Documentation, https://github.com/potatoeggy/noveldown
Project-URL: Repository, https://github.com/potatoeggy/noveldown
